ontology_loader/__init__.py
ontology_loader/cli.py
ontology_loader/mongo_db_config.py
ontology_loader/mongodb_loader.py
ontology_loader/ontology_load_controller.py
ontology_loader/ontology_processor.py
ontology_loader/reporter.py
ontology_loader/utils.py
ontology_loader-0.2.2.dist-info/METADATA
ontology_loader-0.2.2.dist-info/WHEEL
ontology_loader-0.2.2.dist-info/entry_points.txt
ontology_loader-0.2.2.dist-info/RECORD
