Metadata-Version: 2.3
Name: ontology-loader
Version: 0.2.2
Summary: ontology_loader
License: MIT
Author: Sierra Moxon
Author-email: smoxon@lbl.gov
Requires-Python: >=3.10,<4.0
Classifier: License :: OSI Approved :: MIT License
Classifier: Programming Language :: Python :: 3
Classifier: Programming Language :: Python :: 3.10
Classifier: Programming Language :: Python :: 3.11
Classifier: Programming Language :: Python :: 3.12
Classifier: Programming Language :: Python :: 3.13
Requires-Dist: click (>=8.1.7,<9.0.0)
Requires-Dist: curies (>=0.9.1)
Requires-Dist: linkml-store (>=0.2.10)
Requires-Dist: mongomock (>=4.3.0,<5.0.0)
Requires-Dist: motor (>=3.6.0,<4.0.0)
Requires-Dist: neo4j (>=5.25.0,<6.0.0)
Requires-Dist: nmdc-schema
Requires-Dist: oaklib (>=0.6.16,<0.7.0)
Requires-Dist: pymongo (>=4.9.1,<5.0.0)
Requires-Dist: pystow (>=0.5.0,<0.6.0)
Requires-Dist: pytest (>=8.3.4,<9.0.0)
Requires-Dist: tabulate (>=0.9.0,<0.10.0)
Requires-Dist: tiktoken (>=0.8.0,<0.9.0)
Requires-Dist: tox (>=4.24.1,<5.0.0)
